{
    "data": {
        "header": {
            "title":"ジャンプ率ジェネレーター",
            "text": "文字ジャンプ率を動的に変えることができます"
        },
        "main": {
            "title":"ジャンプ率ジェネレーター",
            "text": "行長、行間、ジャンプ率などを変えてみてください。"
        },
        "about": {
            "title":"このアプリについて",
            "text": "文字の行長、行間、ジャンプ率を動的に変更した画面を確認することができます。"
        },
        "inner": [
            {
            "title": "CSS（文字色）",
            "text": "CSSでタイトルの文字色変更。"
            },
            {
            "title":"JS（文字列）",
            "text": "JSでテキストの文字列追加「<span class='hello'></span>」"
            }
        ],
        "footer": {
            "text":"©️jump-rate-generator"
        }
    }
}